orbis_addon_repoman/__init__.py
orbis_addon_repoman/main.py
orbis_addon_repoman/sources.yaml
orbis_addon_repoman/corpora/__init__.py
orbis_addon_repoman/corpora/main.py
orbis_addon_repoman/corpora/gerbil/__init__.py
orbis_addon_repoman/corpora/gerbil/main.py
orbis_addon_repoman/corpora/local/__init__.py
orbis_addon_repoman/corpora/local/main.py
orbis_addon_repoman/format/__init__.py
orbis_addon_repoman/format/json/__init__.py
orbis_addon_repoman/format/json/annotation.py
orbis_addon_repoman/format/json/folder.py
orbis_addon_repoman/format/json/main.py
orbis_addon_repoman/format/nif/__init__.py
orbis_addon_repoman/format/nif/convert.py
orbis_addon_repoman/format/nif/main.py
orbis_addon_repoman/monocle/__init__.py
orbis_addon_repoman/monocle/filter_downloader.py
orbis_addon_repoman/monocle/lense_downloader.py
orbis_addon_repoman/monocle/main.py
orbis_addon_repoman/monocle/map_downloader.py
orbis_addon_repoman-2.4.0.dist-info/LICENSE
orbis_addon_repoman-2.4.0.dist-info/METADATA
orbis_addon_repoman-2.4.0.dist-info/WHEEL
orbis_addon_repoman-2.4.0.dist-info/top_level.txt
orbis_addon_repoman-2.4.0.dist-info/RECORD
