Metadata-Version: 2.1
Name: orbis-addon-repoman
Version: 2.4.0
Summary: The Repoman Addon for Orbis to download and install Corpora and Monocle files.
Home-page: https://github.com/orbis-eval/orbis_addon_repoman
Author: fabod, Roger Waldvogel
License: GPL2
Platform: UNKNOWN
Requires-Python: >3.6
Requires-Dist: jsonschema
Requires-Dist: rdflib (>=4.2.2)
